primapy_tracing/__init__.py
primapy_tracing/py.typed
primapy_tracing-0.0.1.dist-info/WHEEL
primapy_tracing-0.0.1.dist-info/METADATA
primapy_tracing-0.0.1.dist-info/RECORD
